vim_bridge/__init__.py
vim_bridge/registry.py
vim_bridge3-0.6.dist-info/DESCRIPTION.rst
vim_bridge3-0.6.dist-info/METADATA
vim_bridge3-0.6.dist-info/RECORD
vim_bridge3-0.6.dist-info/WHEEL
vim_bridge3-0.6.dist-info/metadata.json
vim_bridge3-0.6.dist-info/top_level.txt
