Metadata-Version: 2.0
Name: vim-bridge3
Version: 0.6
Summary: A Python3-to-Vim bridge decorator that allows transparent calls to Python 3 functions in native Vim scripts.
Home-page: http://github.com/rpuntaie/vim_bridge
Author: Vincent Driessen
Author-email: vincent@datafox.nl
License: BSD
Platform: any
Classifier: Development Status :: 4 - Beta
Classifier: Operating System :: OS Independent
Classifier: Programming Language :: Python
Classifier: Programming Language :: Python :: 3.5
Classifier: Programming Language :: Python :: 3.6
Classifier: Intended Audience :: Developers
Classifier: License :: OSI Approved :: BSD License
Classifier: Operating System :: POSIX
Classifier: Topic :: Text Editors
